pipuck/__init__.py
pipuck/epuck.py
pipuck/epuck1.py
pipuck/epuck2.py
pipuck/ft903.py
pipuck/lsm9ds1.py
pipuck/mcp23017.py
pipuck/pipuck.py
pipuck/tof_sensor.py
pipuck/yrl_expansion.py
pipuck-0.0.1.dist-info/LICENSE
pipuck-0.0.1.dist-info/METADATA
pipuck-0.0.1.dist-info/WHEEL
pipuck-0.0.1.dist-info/top_level.txt
pipuck-0.0.1.dist-info/RECORD
