Metadata-Version: 2.1
Name: pipuck
Version: 0.0.1
Summary: Pi-puck robot Python library
Home-page: https://github.com/yorkrobotlab/pi-puck
Author: Russell Joyce
Author-email: russell.joyce@york.ac.uk
Project-URL: Bug Tracker, https://github.com/yorkrobotlab/pi-puck/issues
Classifier: Programming Language :: Python :: 3
Classifier: License :: OSI Approved :: MIT License
Classifier: Operating System :: POSIX :: Linux
Requires-Python: >=3.6
License-File: LICENSE
